sqlalchemy_annotations/__init__.py
sqlalchemy_annotations/_booleans.py
sqlalchemy_annotations/_dates.py
sqlalchemy_annotations/_enums.py
sqlalchemy_annotations/_numbers.py
sqlalchemy_annotations/_strings.py
sqlalchemy_annotations/_uuids.py
sqlalchemy_annotations-0.0.2.dist-info/licenses/LICENSE
sqlalchemy_annotations-0.0.2.dist-info/METADATA
sqlalchemy_annotations-0.0.2.dist-info/WHEEL
sqlalchemy_annotations-0.0.2.dist-info/top_level.txt
sqlalchemy_annotations-0.0.2.dist-info/RECORD
