Metadata-Version: 2.4
Name: sqlalchemy-annotations
Version: 0.0.2
Summary: Table column annotations for SQLAlchemy
Author-email: Mikhail Shagov <mishaga@me.com>
Maintainer-email: Mikhail Shagov <mishaga@me.com>
License-Expression: MIT
Project-URL: Homepage, https://github.com/mishaga/sqlalchemy-annotations
Project-URL: Issues, https://github.com/mishaga/sqlalchemy-annotations/issues
Classifier: Development Status :: 5 - Production/Stable
Classifier: Programming Language :: Python
Classifier: Programming Language :: Python :: Implementation :: CPython
Classifier: Programming Language :: Python :: 3
Classifier: Programming Language :: Python :: 3 :: Only
Classifier: Programming Language :: Python :: 3.10
Classifier: Programming Language :: Python :: 3.11
Classifier: Programming Language :: Python :: 3.12
Classifier: Programming Language :: Python :: 3.13
Classifier: Intended Audience :: Developers
Classifier: Intended Audience :: Information Technology
Classifier: Operating System :: OS Independent
Classifier: Topic :: Software Development :: Libraries :: Python Modules
Classifier: Topic :: Internet
Requires-Python: >=3.10
License-File: LICENSE
Requires-Dist: sqlalchemy==2.*
Dynamic: license-file
